{
  "version": 1,
  "policy": "add-only classification for JS files unreachable from src/index.js static require graph",
  "items": [
    {
      "file": "src/repos/firestore/indexFallbackPolicy.js",
      "status": "frozen",
      "reachability": "non_reachable_runtime",
      "disposition": "future_deletion_candidate",
      "reason": "runtime route graph では未到達だが、fallback policy仕様のSSOT参照を維持するため凍結管理",
      "ssot_refs": [
        "scripts/check_structural_cleanup.js",
        "docs/INDEX_PLAN.md",
        "docs/REPO_FULL_AUDIT_REPORT_2026-02-27.md"
      ]
    },
    {
      "file": "src/shared/phaseDocPathResolver.js",
      "status": "monitor",
      "reachability": "build_time_only",
      "disposition": "keep_as_build_helper",
      "reason": "runtime graphでは未到達だが、phase path map生成スクリプトが利用する build-time helper",
      "ssot_refs": [
        "scripts/generate_phase_path_map.js",
        "scripts/check_structural_cleanup.js",
        "docs/PHASE_PATH_MAP.json"
      ]
    },
    {
      "file": "src/domain/qualityPatrol/buildBacklogRecord.js",
      "status": "monitor",
      "reachability": "non_reachable_runtime",
      "disposition": "future_deletion_candidate",
      "reason": "PR-1 foundation only; backlog builder is intentionally caller-less until later patrol wiring PRs land",
      "ssot_refs": [
        "docs/QUALITY_PATROL_REGISTRY_RUNBOOK.md",
        "scripts/check_structural_cleanup.js"
      ]
    },
    {
      "file": "src/domain/qualityPatrol/buildIssueRecord.js",
      "status": "monitor",
      "reachability": "non_reachable_runtime",
      "disposition": "future_deletion_candidate",
      "reason": "PR-1 foundation only; issue builder is intentionally caller-less until later patrol wiring PRs land",
      "ssot_refs": [
        "docs/QUALITY_PATROL_REGISTRY_RUNBOOK.md",
        "scripts/check_structural_cleanup.js"
      ]
    },
    {
      "file": "src/domain/qualityPatrol/dedupe.js",
      "status": "monitor",
      "reachability": "non_reachable_runtime",
      "disposition": "future_deletion_candidate",
      "reason": "PR-1 foundation only; dedupe helper is reserved for future patrol detection callers",
      "ssot_refs": [
        "docs/QUALITY_PATROL_REGISTRY_RUNBOOK.md",
        "scripts/check_structural_cleanup.js"
      ]
    },
    {
      "file": "src/domain/qualityPatrol/fingerprint.js",
      "status": "monitor",
      "reachability": "non_reachable_runtime",
      "disposition": "future_deletion_candidate",
      "reason": "PR-1 foundation only; fingerprint helper is reserved for future patrol issue upsert callers",
      "ssot_refs": [
        "docs/QUALITY_PATROL_REGISTRY_RUNBOOK.md",
        "scripts/check_structural_cleanup.js"
      ]
    },
    {
      "file": "src/domain/qualityPatrol/issueModel.js",
      "status": "monitor",
      "reachability": "non_reachable_runtime",
      "disposition": "future_deletion_candidate",
      "reason": "PR-1 foundation only; issue model constants are intentionally not runtime-wired yet",
      "ssot_refs": [
        "docs/QUALITY_PATROL_REGISTRY_RUNBOOK.md",
        "scripts/check_structural_cleanup.js"
      ]
    },
    {
      "file": "src/domain/qualityPatrol/normalizeSeverity.js",
      "status": "monitor",
      "reachability": "non_reachable_runtime",
      "disposition": "future_deletion_candidate",
      "reason": "PR-1 foundation only; severity normalization is reserved for later patrol issue callers",
      "ssot_refs": [
        "docs/QUALITY_PATROL_REGISTRY_RUNBOOK.md",
        "scripts/check_structural_cleanup.js"
      ]
    },
    {
      "file": "src/domain/qualityPatrol/normalizeStatus.js",
      "status": "monitor",
      "reachability": "non_reachable_runtime",
      "disposition": "future_deletion_candidate",
      "reason": "PR-1 foundation only; status normalization is reserved for later patrol issue callers",
      "ssot_refs": [
        "docs/QUALITY_PATROL_REGISTRY_RUNBOOK.md",
        "scripts/check_structural_cleanup.js"
      ]
    },
    {
      "file": "src/repos/firestore/improvementBacklogRepo.js",
      "status": "monitor",
      "reachability": "non_reachable_runtime",
      "disposition": "future_deletion_candidate",
      "reason": "PR-1 foundation only; backlog repo is intentionally not wired to runtime routes or jobs yet",
      "ssot_refs": [
        "docs/QUALITY_PATROL_REGISTRY_RUNBOOK.md",
        "scripts/check_structural_cleanup.js"
      ]
    },
    {
      "file": "src/repos/firestore/qualityIssueRegistryRepo.js",
      "status": "monitor",
      "reachability": "non_reachable_runtime",
      "disposition": "future_deletion_candidate",
      "reason": "PR-1 foundation only; issue registry repo is intentionally not wired to runtime routes or jobs yet",
      "ssot_refs": [
        "docs/QUALITY_PATROL_REGISTRY_RUNBOOK.md",
        "scripts/check_structural_cleanup.js"
      ]
    },
    {
      "file": "src/usecases/qualityPatrol/listOpenIssues.js",
      "status": "monitor",
      "reachability": "non_reachable_runtime",
      "disposition": "future_deletion_candidate",
      "reason": "PR-1 foundation only; query helper is reserved for later operator/query layers",
      "ssot_refs": [
        "docs/QUALITY_PATROL_REGISTRY_RUNBOOK.md",
        "scripts/check_structural_cleanup.js"
      ]
    },
    {
      "file": "src/usecases/qualityPatrol/listTopPriorityBacklog.js",
      "status": "monitor",
      "reachability": "non_reachable_runtime",
      "disposition": "future_deletion_candidate",
      "reason": "PR-1 foundation only; query helper is reserved for later operator/query layers",
      "ssot_refs": [
        "docs/QUALITY_PATROL_REGISTRY_RUNBOOK.md",
        "scripts/check_structural_cleanup.js"
      ]
    },
    {
      "file": "src/usecases/qualityPatrol/upsertImprovementBacklog.js",
      "status": "monitor",
      "reachability": "non_reachable_runtime",
      "disposition": "future_deletion_candidate",
      "reason": "PR-1 foundation only; backlog upsert usecase is reserved for later patrol planners and jobs",
      "ssot_refs": [
        "docs/QUALITY_PATROL_REGISTRY_RUNBOOK.md",
        "scripts/check_structural_cleanup.js"
      ]
    },
    {
      "file": "src/usecases/qualityPatrol/upsertQualityIssue.js",
      "status": "monitor",
      "reachability": "non_reachable_runtime",
      "disposition": "future_deletion_candidate",
      "reason": "PR-1 foundation only; issue upsert usecase is reserved for later patrol detectors and jobs",
      "ssot_refs": [
        "docs/QUALITY_PATROL_REGISTRY_RUNBOOK.md",
        "scripts/check_structural_cleanup.js"
      ]
    },
    {
      "file": "src/domain/qualityPatrol/transcript/buildConversationReviewUnits.js",
      "status": "monitor",
      "reachability": "non_reachable_runtime",
      "disposition": "future_deletion_candidate",
      "reason": "PR-2 foundation only; review unit builder is intentionally caller-limited until evaluator/query layers land",
      "ssot_refs": [
        "docs/QUALITY_PATROL_REVIEW_UNITS_RUNBOOK.md",
        "scripts/check_structural_cleanup.js"
      ]
    },
    {
      "file": "src/domain/qualityPatrol/transcript/buildObservationBlockers.js",
      "status": "monitor",
      "reachability": "non_reachable_runtime",
      "disposition": "future_deletion_candidate",
      "reason": "PR-2 foundation only; blocker builder is reserved for later review and detection callers",
      "ssot_refs": [
        "docs/QUALITY_PATROL_REVIEW_UNITS_RUNBOOK.md",
        "scripts/check_structural_cleanup.js"
      ]
    },
    {
      "file": "src/domain/qualityPatrol/transcript/classifyConversationSlice.js",
      "status": "monitor",
      "reachability": "non_reachable_runtime",
      "disposition": "future_deletion_candidate",
      "reason": "PR-2 foundation only; slice classifier is intentionally isolated until downstream patrol evaluators adopt it",
      "ssot_refs": [
        "docs/QUALITY_PATROL_REVIEW_UNITS_RUNBOOK.md",
        "scripts/check_structural_cleanup.js"
      ]
    },
    {
      "file": "src/domain/qualityPatrol/transcript/constants.js",
      "status": "monitor",
      "reachability": "non_reachable_runtime",
      "disposition": "future_deletion_candidate",
      "reason": "PR-2 foundation only; transcript extractor constants are intentionally isolated until later patrol wiring PRs land",
      "ssot_refs": [
        "docs/QUALITY_PATROL_REVIEW_UNITS_RUNBOOK.md",
        "scripts/check_structural_cleanup.js"
      ]
    },
    {
      "file": "src/domain/qualityPatrol/transcript/normalizeReviewEvidence.js",
      "status": "monitor",
      "reachability": "non_reachable_runtime",
      "disposition": "future_deletion_candidate",
      "reason": "PR-2 foundation only; evidence normalization is reserved for later evaluator and query callers",
      "ssot_refs": [
        "docs/QUALITY_PATROL_REVIEW_UNITS_RUNBOOK.md",
        "scripts/check_structural_cleanup.js"
      ]
    },
    {
      "file": "src/usecases/qualityPatrol/buildConversationReviewUnitsFromSources.js",
      "status": "monitor",
      "reachability": "non_reachable_runtime",
      "disposition": "future_deletion_candidate",
      "reason": "PR-2 foundation only; extractor usecase is intentionally not wired to runtime routes, jobs, or admin surfaces yet",
      "ssot_refs": [
        "docs/QUALITY_PATROL_REVIEW_UNITS_RUNBOOK.md",
        "scripts/check_structural_cleanup.js"
      ]
    },
    {
      "file": "src/domain/qualityPatrol/buildConversationQualityEvidence.js",
      "status": "monitor",
      "reachability": "non_reachable_runtime",
      "disposition": "future_deletion_candidate",
      "reason": "PR-3 foundation only; evaluator evidence builder is intentionally caller-less until KPI and detection layers land",
      "ssot_refs": [
        "docs/QUALITY_PATROL_EVALUATOR_RUNBOOK.md",
        "scripts/check_structural_cleanup.js"
      ]
    },
    {
      "file": "src/domain/qualityPatrol/buildPatrolKpis.js",
      "status": "monitor",
      "reachability": "non_reachable_runtime",
      "disposition": "future_deletion_candidate",
      "reason": "PR-4 foundation only; KPI builder is intentionally not wired to detector, query, or scheduler layers yet",
      "ssot_refs": [
        "docs/QUALITY_PATROL_KPI_RUNBOOK.md",
        "scripts/check_structural_cleanup.js"
      ]
    },
    {
      "file": "src/domain/qualityPatrol/constants.js",
      "status": "monitor",
      "reachability": "non_reachable_runtime",
      "disposition": "future_deletion_candidate",
      "reason": "PR-3 foundation only; evaluator constants remain isolated until future patrol layers consume them",
      "ssot_refs": [
        "docs/QUALITY_PATROL_EVALUATOR_RUNBOOK.md",
        "scripts/check_structural_cleanup.js"
      ]
    },
    {
      "file": "src/domain/qualityPatrol/evaluateConversationQuality.js",
      "status": "monitor",
      "reachability": "non_reachable_runtime",
      "disposition": "future_deletion_candidate",
      "reason": "PR-3 foundation only; evaluator entrypoint is intentionally not wired to registry, UI, or jobs yet",
      "ssot_refs": [
        "docs/QUALITY_PATROL_EVALUATOR_RUNBOOK.md",
        "scripts/check_structural_cleanup.js"
      ]
    },
    {
      "file": "src/domain/qualityPatrol/issueCandidates.js",
      "status": "monitor",
      "reachability": "non_reachable_runtime",
      "disposition": "future_deletion_candidate",
      "reason": "PR-3 foundation only; issue candidate helper is reserved for future detector and registry callers",
      "ssot_refs": [
        "docs/QUALITY_PATROL_EVALUATOR_RUNBOOK.md",
        "scripts/check_structural_cleanup.js"
      ]
    },
    {
      "file": "src/domain/qualityPatrol/kpi/aggregateIssueCandidateMetric.js",
      "status": "monitor",
      "reachability": "non_reachable_runtime",
      "disposition": "future_deletion_candidate",
      "reason": "PR-4 foundation only; issue-candidate KPI aggregation is reserved for later detector and query consumers",
      "ssot_refs": [
        "docs/QUALITY_PATROL_KPI_RUNBOOK.md",
        "scripts/check_structural_cleanup.js"
      ]
    },
    {
      "file": "src/domain/qualityPatrol/kpi/aggregateSignalMetric.js",
      "status": "monitor",
      "reachability": "non_reachable_runtime",
      "disposition": "future_deletion_candidate",
      "reason": "PR-4 foundation only; signal aggregation stays isolated until future patrol KPI callers land",
      "ssot_refs": [
        "docs/QUALITY_PATROL_KPI_RUNBOOK.md",
        "scripts/check_structural_cleanup.js"
      ]
    },
    {
      "file": "src/domain/qualityPatrol/kpi/buildMetricEnvelope.js",
      "status": "monitor",
      "reachability": "non_reachable_runtime",
      "disposition": "future_deletion_candidate",
      "reason": "PR-4 foundation only; KPI envelope builder is intentionally caller-limited until detector and query layers reuse it",
      "ssot_refs": [
        "docs/QUALITY_PATROL_KPI_RUNBOOK.md",
        "scripts/check_structural_cleanup.js"
      ]
    },
    {
      "file": "src/domain/qualityPatrol/kpi/constants.js",
      "status": "monitor",
      "reachability": "non_reachable_runtime",
      "disposition": "future_deletion_candidate",
      "reason": "PR-4 foundation only; KPI thresholds remain isolated until later patrol layers tune them",
      "ssot_refs": [
        "docs/QUALITY_PATROL_KPI_RUNBOOK.md",
        "scripts/check_structural_cleanup.js"
      ]
    },
    {
      "file": "src/domain/qualityPatrol/kpi/groupBySlice.js",
      "status": "monitor",
      "reachability": "non_reachable_runtime",
      "disposition": "future_deletion_candidate",
      "reason": "PR-4 foundation only; slice grouping helper is reserved for later KPI/query consumers",
      "ssot_refs": [
        "docs/QUALITY_PATROL_KPI_RUNBOOK.md",
        "scripts/check_structural_cleanup.js"
      ]
    },
    {
      "file": "src/domain/qualityPatrol/kpi/mergeObservationBlockers.js",
      "status": "monitor",
      "reachability": "non_reachable_runtime",
      "disposition": "future_deletion_candidate",
      "reason": "PR-4 foundation only; blocker aggregation helper is intentionally isolated until detector/query layers adopt it",
      "ssot_refs": [
        "docs/QUALITY_PATROL_KPI_RUNBOOK.md",
        "scripts/check_structural_cleanup.js"
      ]
    },
    {
      "file": "src/domain/qualityPatrol/kpi/resolveMetricStatus.js",
      "status": "monitor",
      "reachability": "non_reachable_runtime",
      "disposition": "future_deletion_candidate",
      "reason": "PR-4 foundation only; KPI status resolver is reserved for later detector and query callers",
      "ssot_refs": [
        "docs/QUALITY_PATROL_KPI_RUNBOOK.md",
        "scripts/check_structural_cleanup.js"
      ]
    },
    {
      "file": "src/domain/qualityPatrol/scoreHelpers.js",
      "status": "monitor",
      "reachability": "non_reachable_runtime",
      "disposition": "future_deletion_candidate",
      "reason": "PR-3 foundation only; evaluator score helpers stay isolated until future patrol callers reuse them",
      "ssot_refs": [
        "docs/QUALITY_PATROL_EVALUATOR_RUNBOOK.md",
        "scripts/check_structural_cleanup.js"
      ]
    },
    {
      "file": "src/domain/qualityPatrol/signals/evaluateContinuitySignals.js",
      "status": "monitor",
      "reachability": "non_reachable_runtime",
      "disposition": "future_deletion_candidate",
      "reason": "PR-3 foundation only; continuity evaluator is intentionally caller-limited until KPI and detection layers land",
      "ssot_refs": [
        "docs/QUALITY_PATROL_EVALUATOR_RUNBOOK.md",
        "scripts/check_structural_cleanup.js"
      ]
    },
    {
      "file": "src/domain/qualityPatrol/signals/evaluateFallbackRepetitionSignals.js",
      "status": "monitor",
      "reachability": "non_reachable_runtime",
      "disposition": "future_deletion_candidate",
      "reason": "PR-3 foundation only; fallback repetition evaluator is reserved for later detector/query consumers",
      "ssot_refs": [
        "docs/QUALITY_PATROL_EVALUATOR_RUNBOOK.md",
        "scripts/check_structural_cleanup.js"
      ]
    },
    {
      "file": "src/domain/qualityPatrol/signals/evaluateKnowledgeUseSignals.js",
      "status": "monitor",
      "reachability": "non_reachable_runtime",
      "disposition": "future_deletion_candidate",
      "reason": "PR-3 foundation only; knowledge-use evaluator is intentionally isolated until registry and KPI layers land",
      "ssot_refs": [
        "docs/QUALITY_PATROL_EVALUATOR_RUNBOOK.md",
        "scripts/check_structural_cleanup.js"
      ]
    },
    {
      "file": "src/domain/qualityPatrol/signals/evaluateNaturalnessSignals.js",
      "status": "monitor",
      "reachability": "non_reachable_runtime",
      "disposition": "future_deletion_candidate",
      "reason": "PR-3 foundation only; naturalness evaluator is intentionally isolated until later patrol callers adopt it",
      "ssot_refs": [
        "docs/QUALITY_PATROL_EVALUATOR_RUNBOOK.md",
        "scripts/check_structural_cleanup.js"
      ]
    },
    {
      "file": "src/domain/qualityPatrol/signals/evaluateProceduralUtilitySignals.js",
      "status": "monitor",
      "reachability": "non_reachable_runtime",
      "disposition": "future_deletion_candidate",
      "reason": "PR-3 foundation only; procedural utility evaluator is reserved for later KPI and detector wiring",
      "ssot_refs": [
        "docs/QUALITY_PATROL_EVALUATOR_RUNBOOK.md",
        "scripts/check_structural_cleanup.js"
      ]
    },
    {
      "file": "src/domain/qualityPatrol/signals/evaluateSpecificitySignals.js",
      "status": "monitor",
      "reachability": "non_reachable_runtime",
      "disposition": "future_deletion_candidate",
      "reason": "PR-3 foundation only; specificity evaluator is intentionally not runtime-wired yet",
      "ssot_refs": [
        "docs/QUALITY_PATROL_EVALUATOR_RUNBOOK.md",
        "scripts/check_structural_cleanup.js"
      ]
    },
    {
      "file": "src/domain/qualityPatrol/signals/evaluateToneSafetySignals.js",
      "status": "monitor",
      "reachability": "non_reachable_runtime",
      "disposition": "future_deletion_candidate",
      "reason": "PR-3 foundation only; tone safety helper stays internal until later evaluator wiring broadens",
      "ssot_refs": [
        "docs/QUALITY_PATROL_EVALUATOR_RUNBOOK.md",
        "scripts/check_structural_cleanup.js"
      ]
    },
    {
      "file": "src/usecases/qualityPatrol/evaluateConversationReviewUnits.js",
      "status": "monitor",
      "reachability": "non_reachable_runtime",
      "disposition": "future_deletion_candidate",
      "reason": "PR-3 foundation only; evaluator usecase is intentionally not wired to routes, jobs, or registry upserts yet",
      "ssot_refs": [
        "docs/QUALITY_PATROL_EVALUATOR_RUNBOOK.md",
        "scripts/check_structural_cleanup.js"
      ]
    },
    {
      "file": "src/usecases/qualityPatrol/buildPatrolKpisFromEvaluations.js",
      "status": "monitor",
      "reachability": "non_reachable_runtime",
      "disposition": "future_deletion_candidate",
      "reason": "PR-4 foundation only; KPI usecase is intentionally not wired to registry, routes, or scheduler yet",
      "ssot_refs": [
        "docs/QUALITY_PATROL_KPI_RUNBOOK.md",
        "scripts/check_structural_cleanup.js"
      ]
    }
  ]
}
